trainseat/__init__.py
trainseat-0.1.dist-info/LICENCE.txt
trainseat-0.1.dist-info/METADATA
trainseat-0.1.dist-info/WHEEL
trainseat-0.1.dist-info/top_level.txt
trainseat-0.1.dist-info/RECORD
