Metadata-Version: 2.1
Name: trainseat
Version: 0.1
Summary: This is related to train seat allocation packages
Author: Saral Kumar Kaviti
Author-email: saralkumar28@gmail.com
Classifier: Programming Language :: Python :: 3
Classifier: License :: OSI Approved :: MIT License
Classifier: Operating System :: OS Independent
License-File: LICENCE.txt
